<BackupInst xmlns="http://www.microsoft.com/GroupPolicy/GPOOperations/Manifest"><GPOGuid><![CDATA[{6875B66A-2F6E-4344-9709-5E2E3BB71CFE}]]></GPOGuid><GPODomain><![CDATA[contoso.bborg.net]]></GPODomain><GPODomainGuid><![CDATA[{3198601b-403d-49d1-bd3f-984b1e6fcb98}]]></GPODomainGuid><GPODomainController><![CDATA[LAB1-DC01.contoso.bborg.net]]></GPODomainController><BackupTime><![CDATA[2024-12-16T08:52:30]]></BackupTime><ID><![CDATA[{89FC985D-C4DC-4757-BA80-5DB2373C5F82}]]></ID><Comment><![CDATA[]]></Comment><GPODisplayName><![CDATA[C - Azure Arc Deployment]]></GPODisplayName></BackupInst>
